validatrix/__init__.py
validatrix/Internal_DAC_interface/Internal_DAC_interface.py
validatrix/Internal_DAC_interface/__init__.py
validatrix/Internal_RS485_master_interface/Internal_RS485_device_data.py
validatrix/Internal_RS485_master_interface/Internal_RS485_master.py
validatrix/Internal_RS485_master_interface/Internal_RS485_master_server.py
validatrix/Internal_RS485_master_interface/__init__.py
validatrix/Internal_RS485_slave_interface/Internal_RS485_device_data.py
validatrix/Internal_RS485_slave_interface/Internal_RS485_slave.py
validatrix/Internal_RS485_slave_interface/Internal_RS485_slave_server.py
validatrix/Internal_RS485_slave_interface/__init__.py
validatrix/Internal_digital_read_interface/Internal_digital_read_interface.py
validatrix/Internal_digital_read_interface/__init__.py
validatrix/automated_test_interface/__init__.py
validatrix/automated_test_interface/automated_test_interface.py
validatrix/common_classes/__init__.py
validatrix/common_classes/all_interfaces_class.py
validatrix/data_collection/__init__.py
validatrix/data_collection/data_collection_interface.py
validatrix/internal_can_interface/__init__.py
validatrix/internal_can_interface/internal_can_interface.py
validatrix/internal_thermistor_emulation/__init__.py
validatrix/internal_thermistor_emulation/internal_thermistor_emulation_interface.py
validatrix/utils/__init__.py
validatrix/utils/helpers.py
validatrix-0.2.71.dist-info/licenses/LICENSE
validatrix-0.2.71.dist-info/METADATA
validatrix-0.2.71.dist-info/WHEEL
validatrix-0.2.71.dist-info/top_level.txt
validatrix-0.2.71.dist-info/RECORD
